{
  "_id": "query_get_s3_file_data_graphql-001",
  "endpoint_id": "query_get_s3_file_data_graphql",
  "endpoint_path": "graphql/GetS3FileData",
  "method": "QUERY",
  "api_version": "graphql",
  "description": "Get paginated CSV file data from S3. Returns S3FileData with rows array (each row as JSON object with column names as keys), limit, offset, and totalRows. Pagination is required for large files (limit: 1-1000, offset: non-negative). CSV files are parsed and returned as structured JSON data. Used by S3FileBrowser component and useS3FileData hook.",
  "created_at": "2026-01-20T00:00:00.000000+00:00",
  "updated_at": "2026-01-20T00:00:00.000000+00:00",
  "endpoint_state": "development",
  "service_file": "appointment360/app/graphql/modules/s3/queries.py",
  "router_file": "contact360/dashboard/src/services/graphql/s3Service.ts",
  "service_methods": [
    "getS3FileData",
    "s3FileData"
  ],
  "repository_methods": [],
  "used_by_pages": [],
  "rate_limit": null,
  "graphql_operation": null,
  "sql_file": null,
  "page_count": 0,
  "access_control": null,
  "lambda_services": null,
  "files": null,
  "methods": null
}