{
  "user_name": "Ricardo Klünter",
  "user_username": "ric-kt",
  "user_bio": "",
  "user_links": "",
  "user_avatar": "https://gravatar.com/avatar/596edcf5cc626ea3be52e8b4d848999ca654c280e2abf26e6683736bb3c7edc6?r=pg&d=retro&size=200",
  "url": "https://n8nworkflows.xyz/workflows/calendly-to-klicktipp-integration-2620\n",
  "url_n8n": "https://n8n.io/workflows/2620",
  "nodeTypes": {
    "n8n-nodes-base.if": {
      "count": 1
    },
    "n8n-nodes-base.set": {
      "count": 2
    },
    "n8n-nodes-base.stickyNote": {
      "count": 1
    },
    "n8n-nodes-klicktipp.klicktipp": {
      "count": 2
    },
    "n8n-nodes-base.calendlyTrigger": {
      "count": 1
    }
  },
  "categories": [
    {
      "id": 11,
      "name": "Other"
    }
  ],
  "workflow_id": "metada-2620"
}