{
  "schema_version": 1,
  "kind": "document",
  "source_path": "promsts/era-prompts/9.x-ecosystem-platformization.md",
  "sha256_source": "0c908689f968b20f87d348decc71dbc99ee614aea5cf2a4c31e305c9b8eae0e5",
  "generated_at": "2026-04-08T23:26:49.441610+00:00",
  "title": "Era 9.x - Ecosystem Integrations and Platformization",
  "front_matter": null,
  "sections": [
    {
      "heading": "Era 9.x - Ecosystem Integrations and Platformization",
      "level": 1,
      "slug": "era-9x---ecosystem-integrations-and-platformization",
      "prose": "- Prompt focus: partner integrations, API gateways, multi-tenant concerns.\n- Require compatibility matrix and operational ownership notes.",
      "tables": [],
      "lists": [
        {
          "ordered": false,
          "items": [
            {
              "text": "Prompt focus: partner integrations, API gateways, multi-tenant concerns.",
              "checked": null
            },
            {
              "text": "Require compatibility matrix and operational ownership notes.",
              "checked": null
            }
          ]
        }
      ],
      "code_blocks": [],
      "links": []
    }
  ],
  "non_parsed_raw_markdown": ""
}