{
  "name": "Delete Email Pattern",
  "request": {
    "type": "http",
    "url": "{{baseUrlV2}}/email-patterns/{{sampleContactUuid}}",
    "scripts": {
      "preRequest": "",
      "postResponse": ""
    },
    "method": "DELETE",
    "queryParams": [],
    "headers": [
      {
        "id": 0,
        "key": "Authorization",
        "value": "Bearer {{accessToken}}",
        "isEnabled": true,
        "description": "",
        "dataType": "string"
      }
    ],
    "body": "",
    "bodyContainer": {
      "text": ""
    },
    "contentType": "text/plain",
    "auth": {
      "currentAuthType": "INHERIT",
      "authConfigStore": {}
    }
  }
}