{
  "services": {
    "EC2/log.server": {
      "path": "EC2/log.server",
      "docker_compose": "EC2/log.server/docker-compose.yml",
      "healthcheck_url": "http://localhost:8091/health",
      "port": 8091,
      "tech_stack": "go-gin",
      "api_prefix": "/",
      "db_profile": "postgres",
      "postman_collection": "docs/backend/postman",
      "checklist_key": "tech-go-gin",
      "era_relevance": [0, 1, 2, 5, 6, 7, 8, 9, 10]
    },
    "EC2/ai.server": {
      "path": "EC2/ai.server",
      "docker_compose": "EC2/ai.server/docker-compose.yml",
      "healthcheck_url": "http://localhost:8090/health",
      "port": 8090,
      "tech_stack": "go-gin",
      "api_prefix": "/",
      "db_profile": "postgres",
      "postman_collection": "docs/backend/postman",
      "checklist_key": "tech-go-gin",
      "era_relevance": [0, 5, 9]
    },
    "EC2/email.server": {
      "path": "EC2/email.server",
      "docker_compose": "EC2/email.server/docker-compose.yml",
      "healthcheck_url": "http://localhost:8086/health",
      "port": 8086,
      "tech_stack": "go-gin",
      "api_prefix": "/",
      "db_profile": "postgres",
      "postman_collection": "docs/backend/postman",
      "checklist_key": "tech-go-gin",
      "era_relevance": [0, 1, 2, 10]
    },
    "EC2/extension.server": {
      "path": "EC2/extension.server",
      "docker_compose": "EC2/extension.server/docker-compose.yml",
      "healthcheck_url": "http://localhost:8092/health",
      "port": 8092,
      "tech_stack": "go-gin",
      "api_prefix": "/v1",
      "db_profile": "postgres",
      "postman_collection": "docs/backend/postman",
      "checklist_key": "tech-go-gin",
      "era_relevance": [4, 9]
    },
    "contact360.io/api": {
      "path": "contact360.io/api",
      "docker_compose": "contact360.io/api/docker-compose.yml",
      "healthcheck_url": "http://localhost:8000/health",
      "port": 8000,
      "tech_stack": "fastapi",
      "api_prefix": "/",
      "db_profile": "postgres",
      "postman_collection": "docs/backend/postman",
      "checklist_key": "tech-django",
      "era_relevance": [0, 1, 2, 3, 4, 5, 6, 7, 8, 9, 10]
    },
    "contact360.io/admin": {
      "path": "contact360.io/admin",
      "docker_compose": "contact360.io/admin/docker-compose.yml",
      "healthcheck_url": "http://localhost:8080/health/",
      "port": 8080,
      "tech_stack": "django",
      "api_prefix": "/",
      "db_profile": "postgres",
      "postman_collection": "docs/backend/postman",
      "checklist_key": "tech-django",
      "era_relevance": [1, 7, 9]
    },
    "contact360.io/root": {
      "path": "contact360.io/root",
      "docker_compose": "contact360.io/root/docker-compose.yml",
      "healthcheck_url": "http://localhost:3001",
      "port": 3001,
      "tech_stack": "nextjs",
      "api_prefix": "/",
      "db_profile": "none",
      "postman_collection": "docs/backend/postman",
      "checklist_key": "tech-nextjs",
      "era_relevance": [0, 9]
    },
    "contact360.io/app": {
      "path": "contact360.io/app",
      "docker_compose": "contact360.io/app/docker-compose.yml",
      "healthcheck_url": "http://localhost:3002",
      "port": 3002,
      "tech_stack": "nextjs",
      "api_prefix": "/",
      "db_profile": "none",
      "postman_collection": "docs/backend/postman",
      "checklist_key": "tech-nextjs",
      "era_relevance": [1, 2, 3, 4, 5, 6, 7, 8, 9, 10]
    },
    "contact360.io/email": {
      "path": "contact360.io/email",
      "docker_compose": "contact360.io/email/docker-compose.yml",
      "healthcheck_url": "http://localhost:3003",
      "port": 3003,
      "tech_stack": "nextjs",
      "api_prefix": "/",
      "db_profile": "none",
      "postman_collection": "docs/backend/postman",
      "checklist_key": "tech-nextjs",
      "era_relevance": [2, 10]
    }
  }
}

