{
  "name": "Generate Company Summary",
  "request": {
    "type": "http",
    "url": "{{baseUrl}}/graphql",
    "scripts": {
      "preRequest": "",
      "postResponse": ""
    },
    "method": "POST",
    "queryParams": [],
    "headers": [
      {
        "id": 0,
        "key": "Content-Type",
        "value": "application/json",
        "isEnabled": true,
        "description": "",
        "dataType": "string"
      },
      {
        "id": 1,
        "key": "Authorization",
        "value": "Bearer{{accessToken}}",
        "isEnabled": true,
        "description": "",
        "dataType": "string"
      }
    ],
    "body": "{\n\"query\":\"mutation GenerateCompanySummary($input:GenerateCompanySummaryInput!){ aiChats{ generateCompanySummary(input:$input){ summary}}}\",\n\"variables\":{\n\"input\":{\n\"companyName\":\"Acme Corp\",\n\"industry\":\"Technology\"\n}\n}\n}",
    "bodyContainer": {
      "text": "{\n\"query\":\"mutation GenerateCompanySummary($input:GenerateCompanySummaryInput!){ aiChats{ generateCompanySummary(input:$input){ summary}}}\",\n\"variables\":{\n\"input\":{\n\"companyName\":\"Acme Corp\",\n\"industry\":\"Technology\"\n}\n}\n}"
    },
    "contentType": "text/plain",
    "auth": {
      "currentAuthType": "INHERIT",
      "authConfigStore": {}
    }
  }
}